[
  {
    "id": 1034569419417178112,
    "conversation_id": "1034569419417178112",
    "created_at": "2018-08-28 18:32:25 EDT",
    "date": "2018-08-28",
    "time": "18:32:25",
    "timezone": "-0400",
    "user_id": 85165134,
    "username": "socialistdogmom",
    "name": "molly conger",
    "place": "",
    "tweet": "two of the concerns from the last meeting have been addressed: we\u2019ve got printed agendas &amp; two pizzas have been provided for board members.  the meeting should begin momentarily...  https://t.co/9U8S0E1y6y",
    "language": "en",
    "mentions": [],
    "urls": [],
    "photos": [
      "https://pbs.twimg.com/media/DluHXD0XsAAYnZX.jpg"
    ],
    "replies_count": 4,
    "retweets_count": 1,
    "likes_count": 33,
    "hashtags": [],
    "cashtags": [],
    "link": "https://twitter.com/socialistdogmom/status/1034569419417178112",
    "retweet": false,
    "quote_url": "",
    "video": 1,
    "thumbnail": "https://pbs.twimg.com/media/DluHXD0XsAAYnZX.jpg",
    "near": "",
    "geo": "",
    "source": "",
    "user_rt_id": "",
    "user_rt": "",
    "retweet_id": "",
    "reply_to": [],
    "retweet_date": "",
    "translate": "",
    "trans_src": "",
    "trans_dest": ""
  },
  {
    "id": 1034570371750670336,
    "conversation_id": "1034569419417178112",
    "created_at": "2018-08-28 18:36:12 EDT",
    "date": "2018-08-28",
    "time": "18:36:12",
    "timezone": "-0400",
    "user_id": 85165134,
    "username": "socialistdogmom",
    "name": "molly conger",
    "place": "",
    "tweet": "as mentioned at the last meeting, we\u2019ll be hearing a presentation tonight from LAJC about how police civilian review boards work in other localities. (board member josh bowers said \u201cstudents,\u201d but i recognize a friend &amp; attorney from LAJC queuing up a ppt)  https://t.co/G8C1m2ZGaw",
    "language": "en",
    "mentions": [],
    "urls": [
      "https://twitter.com/socialistdogmom/status/1030250786402590720?s=21"
    ],
    "photos": [],
    "replies_count": 1,
    "retweets_count": 0,
    "likes_count": 3,
    "hashtags": [],
    "cashtags": [],
    "link": "https://twitter.com/socialistdogmom/status/1034570371750670336",
    "retweet": false,
    "quote_url": "https://twitter.com/socialistdogmom/status/1030250786402590720?s=21",
    "video": 0,
    "thumbnail": "",
    "near": "",
    "geo": "",
    "source": "",
    "user_rt_id": "",
    "user_rt": "",
    "retweet_id": "",
    "reply_to": [],
    "retweet_date": "",
    "translate": "",
    "trans_src": "",
    "trans_dest": ""
  },
  {
    "id": 1034570823955300352,
    "conversation_id": "1034569419417178112",
    "created_at": "2018-08-28 18:38:00 EDT",
    "date": "2018-08-28",
    "time": "18:38:00",
    "timezone": "-0400",
    "user_id": 85165134,
    "username": "socialistdogmom",
    "name": "molly conger",
    "place": "",
    "tweet": "brand new city attorney john blair, mayor nikuyah walker &amp; vice mayor heather hill are seated at the table with the board tonight. counsel for the southern states police benevolent association, denise lunsford, is present in the audience.",
    "language": "en",
    "mentions": [],
    "urls": [],
    "photos": [],
    "replies_count": 1,
    "retweets_count": 0,
    "likes_count": 1,
    "hashtags": [],
    "cashtags": [],
    "link": "https://twitter.com/socialistdogmom/status/1034570823955300352",
    "retweet": false,
    "quote_url": "",
    "video": 0,
    "thumbnail": "",
    "near": "",
    "geo": "",
    "source": "",
    "user_rt_id": "",
    "user_rt": "",
    "retweet_id": "",
    "reply_to": [],
    "retweet_date": "",
    "translate": "",
    "trans_src": "",
    "trans_dest": ""
  },
  {
    "id": 1034571263774273537,
    "conversation_id": "1034569419417178112",
    "created_at": "2018-08-28 18:39:45 EDT",
    "date": "2018-08-28",
    "time": "18:39:45",
    "timezone": "-0400",
    "user_id": 85165134,
    "username": "socialistdogmom",
    "name": "molly conger",
    "place": "",
    "tweet": "this basement conference room is NOT large enough \u2014 it\u2019s a packed house.  board member reverend don gathers again assuming the role of meeting chair. no one responded to the call for public comment, so we\u2019re getting started &amp; moving on.",
    "language": "en",
    "mentions": [],
    "urls": [],
    "photos": [],
    "replies_count": 1,
    "retweets_count": 0,
    "likes_count": 2,
    "hashtags": [],
    "cashtags": [],
    "link": "https://twitter.com/socialistdogmom/status/1034571263774273537",
    "retweet": false,
    "quote_url": "",
    "video": 0,
    "thumbnail": "",
    "near": "",
    "geo": "",
    "source": "",
    "user_rt_id": "",
    "user_rt": "",
    "retweet_id": "",
    "reply_to": [],
    "retweet_date": "",
    "translate": "",
    "trans_src": "",
    "trans_dest": ""
  },
  {
    "id": 1034572221145145350,
    "conversation_id": "1034569419417178112",
    "created_at": "2018-08-28 18:43:33 EDT",
    "date": "2018-08-28",
    "time": "18:43:33",
    "timezone": "-0400",
    "user_id": 85165134,
    "username": "socialistdogmom",
    "name": "molly conger",
    "place": "",
    "tweet": "city attorney john blair says he talked to the counsel for fairfax county \u2014 in fairfax county, they hired outside counsel to represent the CRB. in virginia beach, the city attorney\u2019s office does represent their CRB.",
    "language": "en",
    "mentions": [],
    "urls": [],
    "photos": [],
    "replies_count": 1,
    "retweets_count": 0,
    "likes_count": 2,
    "hashtags": [],
    "cashtags": [],
    "link": "https://twitter.com/socialistdogmom/status/1034572221145145350",
    "retweet": false,
    "quote_url": "",
    "video": 0,
    "thumbnail": "",
    "near": "",
    "geo": "",
    "source": "",
    "user_rt_id": "",
    "user_rt": "",
    "retweet_id": "",
    "reply_to": [],
    "retweet_date": "",
    "translate": "",
    "trans_src": "",
    "trans_dest": ""
  },
  {
    "id": 1034572226153078785,
    "conversation_id": "1034569419417178112",
    "created_at": "2018-08-28 18:43:34 EDT",
    "date": "2018-08-28",
    "time": "18:43:34",
    "timezone": "-0400",
    "user_id": 85165134,
    "username": "socialistdogmom",
    "name": "molly conger",
    "place": "",
    "tweet": "cville city atty john blair, on representing the police civilian review board: \u201cour office...depending on your charter\u201d ... \u201cwe\u2019d be happy to look at that issue from an ethical perspective\u201d",
    "language": "en",
    "mentions": [],
    "urls": [],
    "photos": [],
    "replies_count": 1,
    "retweets_count": 0,
    "likes_count": 2,
    "hashtags": [],
    "cashtags": [],
    "link": "https://twitter.com/socialistdogmom/status/1034572226153078785",
    "retweet": false,
    "quote_url": "",
    "video": 0,
    "thumbnail": "",
    "near": "",
    "geo": "",
    "source": "",
    "user_rt_id": "",
    "user_rt": "",
    "retweet_id": "",
    "reply_to": [],
    "retweet_date": "",
    "translate": "",
    "trans_src": "",
    "trans_dest": ""
  },
  {
    "id": 1034572224139644929,
    "conversation_id": "1034569419417178112",
    "created_at": "2018-08-28 18:43:34 EDT",
    "date": "2018-08-28",
    "time": "18:43:34",
    "timezone": "-0400",
    "user_id": 85165134,
    "username": "socialistdogmom",
    "name": "molly conger",
    "place": "",
    "tweet": "this was discussed at the last meeting as a likely conflict of interest with the city attorney\u2019s office possibly representing both police &amp; the board seeking to hold them accountable.   https://t.co/5haX7ngBe8",
    "language": "en",
    "mentions": [],
    "urls": [
      "https://twitter.com/socialistdogmom/status/1030237890062766081?s=21"
    ],
    "photos": [],
    "replies_count": 1,
    "retweets_count": 0,
    "likes_count": 2,
    "hashtags": [],
    "cashtags": [],
    "link": "https://twitter.com/socialistdogmom/status/1034572224139644929",
    "retweet": false,
    "quote_url": "https://twitter.com/socialistdogmom/status/1030237890062766081?s=21",
    "video": 0,
    "thumbnail": "",
    "near": "",
    "geo": "",
    "source": "",
    "user_rt_id": "",
    "user_rt": "",
    "retweet_id": "",
    "reply_to": [],
    "retweet_date": "",
    "translate": "",
    "trans_src": "",
    "trans_dest": ""
  },
  {
    "id": 1034572784654012422,
    "conversation_id": "1034569419417178112",
    "created_at": "2018-08-28 18:45:47 EDT",
    "date": "2018-08-28",
    "time": "18:45:47",
    "timezone": "-0400",
    "user_id": 85165134,
    "username": "socialistdogmom",
    "name": "molly conger",
    "place": "",
    "tweet": "board member sarah burke asking heather hill for clarification on an email from council stating that the board currently exists to draft bylaws &amp; until bylaws are written &amp; accepted by council, the board doesn\u2019t have the \u201cfunctionality\u201d of the final board.",
    "language": "en",
    "mentions": [],
    "urls": [],
    "photos": [],
    "replies_count": 2,
    "retweets_count": 0,
    "likes_count": 3,
    "hashtags": [],
    "cashtags": [],
    "link": "https://twitter.com/socialistdogmom/status/1034572784654012422",
    "retweet": false,
    "quote_url": "",
    "video": 0,
    "thumbnail": "",
    "near": "",
    "geo": "",
    "source": "",
    "user_rt_id": "",
    "user_rt": "",
    "retweet_id": "",
    "reply_to": [],
    "retweet_date": "",
    "translate": "",
    "trans_src": "",
    "trans_dest": ""
  },
  {
    "id": 1034573340189569024,
    "conversation_id": "1034569419417178112",
    "created_at": "2018-08-28 18:48:00 EDT",
    "date": "2018-08-28",
    "time": "18:48:00",
    "timezone": "-0400",
    "user_id": 85165134,
    "username": "socialistdogmom",
    "name": "molly conger",
    "place": "",
    "tweet": "john blair: \u201cthe best step right now would be to try to draft those bylaws\u201d  the subtext here seems to be that council doesn\u2019t want the CRB to DO anything this year. just write bylaws. they\u2019re kicking the can on police accountability.",
    "language": "en",
    "mentions": [],
    "urls": [],
    "photos": [],
    "replies_count": 1,
    "retweets_count": 1,
    "likes_count": 4,
    "hashtags": [],
    "cashtags": [],
    "link": "https://twitter.com/socialistdogmom/status/1034573340189569024",
    "retweet": false,
    "quote_url": "",
    "video": 0,
    "thumbnail": "",
    "near": "",
    "geo": "",
    "source": "",
    "user_rt_id": "",
    "user_rt": "",
    "retweet_id": "",
    "reply_to": [],
    "retweet_date": "",
    "translate": "",
    "trans_src": "",
    "trans_dest": ""
  },
  {
    "id": 1034574085974581248,
    "conversation_id": "1034569419417178112",
    "created_at": "2018-08-28 18:50:58 EDT",
    "date": "2018-08-28",
    "time": "18:50:58",
    "timezone": "-0400",
    "user_id": 85165134,
    "username": "socialistdogmom",
    "name": "molly conger",
    "place": "",
    "tweet": "mayor walker says, in a vague and roundabout way, that they didn\u2019t envision the work of the board beginning until year two. sarah burke pushes back - they need to collect information about things like data privacy in order to write the bylaws.   https://t.co/LgdGvAfFcr",
    "language": "en",
    "mentions": [],
    "urls": [
      "https://twitter.com/socialistdogmom/status/1030237315782926337?s=21"
    ],
    "photos": [],
    "replies_count": 1,
    "retweets_count": 0,
    "likes_count": 4,
    "hashtags": [],
    "cashtags": [],
    "link": "https://twitter.com/socialistdogmom/status/1034574085974581248",
    "retweet": false,
    "quote_url": "https://twitter.com/socialistdogmom/status/1030237315782926337?s=21",
    "video": 0,
    "thumbnail": "",
    "near": "",
    "geo": "",
    "source": "",
    "user_rt_id": "",
    "user_rt": "",
    "retweet_id": "",
    "reply_to": [],
    "retweet_date": "",
    "translate": "",
    "trans_src": "",
    "trans_dest": ""
  },
  {
    "id": 1034574560648200195,
    "conversation_id": "1034569419417178112",
    "created_at": "2018-08-28 18:52:51 EDT",
    "date": "2018-08-28",
    "time": "18:52:51",
    "timezone": "-0400",
    "user_id": 85165134,
    "username": "socialistdogmom",
    "name": "molly conger",
    "place": "",
    "tweet": "heather hill tells the board \u201cyou should be able to access\u201d the current system that collects complaints about police. john blair seems less reassuring - he asks if they are looking for aggregate data (# and type of complaints) or specific information about individual complaints?",
    "language": "en",
    "mentions": [],
    "urls": [],
    "photos": [],
    "replies_count": 1,
    "retweets_count": 0,
    "likes_count": 2,
    "hashtags": [],
    "cashtags": [],
    "link": "https://twitter.com/socialistdogmom/status/1034574560648200195",
    "retweet": false,
    "quote_url": "",
    "video": 0,
    "thumbnail": "",
    "near": "",
    "geo": "",
    "source": "",
    "user_rt_id": "",
    "user_rt": "",
    "retweet_id": "",
    "reply_to": [],
    "retweet_date": "",
    "translate": "",
    "trans_src": "",
    "trans_dest": ""
  },
  {
    "id": 1034574834808889345,
    "conversation_id": "1034569419417178112",
    "created_at": "2018-08-28 18:53:56 EDT",
    "date": "2018-08-28",
    "time": "18:53:56",
    "timezone": "-0400",
    "user_id": 85165134,
    "username": "socialistdogmom",
    "name": "molly conger",
    "place": "",
    "tweet": "sarah burke cites a public comment from the last meeting about residents not receiving required, timely updates about the complaints they\u2019ve filed via the proper, current process. \u201ci know i can FOIA information about the number of complaints. i\u2019ve done that,\u201d she says.",
    "language": "en",
    "mentions": [],
    "urls": [],
    "photos": [],
    "replies_count": 1,
    "retweets_count": 0,
    "likes_count": 1,
    "hashtags": [],
    "cashtags": [],
    "link": "https://twitter.com/socialistdogmom/status/1034574834808889345",
    "retweet": false,
    "quote_url": "",
    "video": 0,
    "thumbnail": "",
    "near": "",
    "geo": "",
    "source": "",
    "user_rt_id": "",
    "user_rt": "",
    "retweet_id": "",
    "reply_to": [],
    "retweet_date": "",
    "translate": "",
    "trans_src": "",
    "trans_dest": ""
  },
  {
    "id": 1034575183749808129,
    "conversation_id": "1034569419417178112",
    "created_at": "2018-08-28 18:55:19 EDT",
    "date": "2018-08-28",
    "time": "18:55:19",
    "timezone": "-0400",
    "user_id": 85165134,
    "username": "socialistdogmom",
    "name": "molly conger",
    "place": "",
    "tweet": "board member juan gonzalez says they need to gather their own information. independently. that the police department\u2019s own information \u201cis the opposite of independent.\u201d sarah says people who have complaints about police may not be comfortable addressing them WITH THE POLICE.",
    "language": "en",
    "mentions": [],
    "urls": [],
    "photos": [],
    "replies_count": 1,
    "retweets_count": 0,
    "likes_count": 7,
    "hashtags": [],
    "cashtags": [],
    "link": "https://twitter.com/socialistdogmom/status/1034575183749808129",
    "retweet": false,
    "quote_url": "",
    "video": 0,
    "thumbnail": "",
    "near": "",
    "geo": "",
    "source": "",
    "user_rt_id": "",
    "user_rt": "",
    "retweet_id": "",
    "reply_to": [],
    "retweet_date": "",
    "translate": "",
    "trans_src": "",
    "trans_dest": ""
  },
  {
    "id": 1034575494849732608,
    "conversation_id": "1034569419417178112",
    "created_at": "2018-08-28 18:56:34 EDT",
    "date": "2018-08-28",
    "time": "18:56:34",
    "timezone": "-0400",
    "user_id": 85165134,
    "username": "socialistdogmom",
    "name": "molly conger",
    "place": "",
    "tweet": "the board also recognizes the issue of privacy concerns if they are collecting their own information. i\u2019m not sure this is a resolvable disconnect - the need for both transparency &amp; privacy.",
    "language": "en",
    "mentions": [],
    "urls": [],
    "photos": [],
    "replies_count": 1,
    "retweets_count": 0,
    "likes_count": 1,
    "hashtags": [],
    "cashtags": [],
    "link": "https://twitter.com/socialistdogmom/status/1034575494849732608",
    "retweet": false,
    "quote_url": "",
    "video": 0,
    "thumbnail": "",
    "near": "",
    "geo": "",
    "source": "",
    "user_rt_id": "",
    "user_rt": "",
    "retweet_id": "",
    "reply_to": [],
    "retweet_date": "",
    "translate": "",
    "trans_src": "",
    "trans_dest": ""
  },
  {
    "id": 1034575953828171776,
    "conversation_id": "1034569419417178112",
    "created_at": "2018-08-28 18:58:23 EDT",
    "date": "2018-08-28",
    "time": "18:58:23",
    "timezone": "-0400",
    "user_id": 85165134,
    "username": "socialistdogmom",
    "name": "molly conger",
    "place": "",
    "tweet": "john blair says the CRBs in fairfax &amp; virginia beach are \u201canother layer in the internal affairs process,\u201d which allows them to keep information about people filing complaints from being FOIA\u2019ed - they\u2019re technically part of personnel records, which are exempt.",
    "language": "en",
    "mentions": [],
    "urls": [],
    "photos": [],
    "replies_count": 1,
    "retweets_count": 1,
    "likes_count": 1,
    "hashtags": [],
    "cashtags": [],
    "link": "https://twitter.com/socialistdogmom/status/1034575953828171776",
    "retweet": false,
    "quote_url": "",
    "video": 0,
    "thumbnail": "",
    "near": "",
    "geo": "",
    "source": "",
    "user_rt_id": "",
    "user_rt": "",
    "retweet_id": "",
    "reply_to": [],
    "retweet_date": "",
    "translate": "",
    "trans_src": "",
    "trans_dest": ""
  },
  {
    "id": 1034576161488158722,
    "conversation_id": "1034569419417178112",
    "created_at": "2018-08-28 18:59:13 EDT",
    "date": "2018-08-28",
    "time": "18:59:13",
    "timezone": "-0400",
    "user_id": 85165134,
    "username": "socialistdogmom",
    "name": "molly conger",
    "place": "",
    "tweet": "john blair says the city attorney\u2019s office can research the issue. that\u2019s a step up from lisa robertson\u2019s visible unwillingness to help during the last meeting, at least?",
    "language": "en",
    "mentions": [],
    "urls": [],
    "photos": [],
    "replies_count": 1,
    "retweets_count": 0,
    "likes_count": 3,
    "hashtags": [],
    "cashtags": [],
    "link": "https://twitter.com/socialistdogmom/status/1034576161488158722",
    "retweet": false,
    "quote_url": "",
    "video": 0,
    "thumbnail": "",
    "near": "",
    "geo": "",
    "source": "",
    "user_rt_id": "",
    "user_rt": "",
    "retweet_id": "",
    "reply_to": [],
    "retweet_date": "",
    "translate": "",
    "trans_src": "",
    "trans_dest": ""
  },
  {
    "id": 1034577081592688641,
    "conversation_id": "1034569419417178112",
    "created_at": "2018-08-28 19:02:52 EDT",
    "date": "2018-08-28",
    "time": "19:02:52",
    "timezone": "-0400",
    "user_id": 85165134,
    "username": "socialistdogmom",
    "name": "molly conger",
    "place": "",
    "tweet": "mayor walker says of the CRB being in \u201cactivity mode\u201d - \u201cyou\u2019re not supposed to be there\u201d until after the final. tales have been written &amp; accepted by council and that council would have to vote on whether they can collect information before that is done.",
    "language": "en",
    "mentions": [],
    "urls": [],
    "photos": [],
    "replies_count": 1,
    "retweets_count": 0,
    "likes_count": 1,
    "hashtags": [],
    "cashtags": [],
    "link": "https://twitter.com/socialistdogmom/status/1034577081592688641",
    "retweet": false,
    "quote_url": "",
    "video": 0,
    "thumbnail": "",
    "near": "",
    "geo": "",
    "source": "",
    "user_rt_id": "",
    "user_rt": "",
    "retweet_id": "",
    "reply_to": [],
    "retweet_date": "",
    "translate": "",
    "trans_src": "",
    "trans_dest": ""
  },
  {
    "id": 1034577084759322625,
    "conversation_id": "1034569419417178112",
    "created_at": "2018-08-28 19:02:53 EDT",
    "date": "2018-08-28",
    "time": "19:02:53",
    "timezone": "-0400",
    "user_id": 85165134,
    "username": "socialistdogmom",
    "name": "molly conger",
    "place": "",
    "tweet": "sarah burke asks for clarification - is research on best practices allowed as part of the bylaw drafting process?",
    "language": "en",
    "mentions": [],
    "urls": [],
    "photos": [],
    "replies_count": 2,
    "retweets_count": 0,
    "likes_count": 1,
    "hashtags": [],
    "cashtags": [],
    "link": "https://twitter.com/socialistdogmom/status/1034577084759322625",
    "retweet": false,
    "quote_url": "",
    "video": 0,
    "thumbnail": "",
    "near": "",
    "geo": "",
    "source": "",
    "user_rt_id": "",
    "user_rt": "",
    "retweet_id": "",
    "reply_to": [],
    "retweet_date": "",
    "translate": "",
    "trans_src": "",
    "trans_dest": ""
  },
  {
    "id": 1034577677108371459,
    "conversation_id": "1034569419417178112",
    "created_at": "2018-08-28 19:05:14 EDT",
    "date": "2018-08-28",
    "time": "19:05:14",
    "timezone": "-0400",
    "user_id": 85165134,
    "username": "socialistdogmom",
    "name": "molly conger",
    "place": "",
    "tweet": "sarah still pushing back on this \u2014 if they don\u2019t properly research how to collect information from residents safely &amp; effectively, they will end up creating a CRB that doesn\u2019t meet the community\u2019s needs.",
    "language": "en",
    "mentions": [],
    "urls": [],
    "photos": [],
    "replies_count": 1,
    "retweets_count": 0,
    "likes_count": 3,
    "hashtags": [],
    "cashtags": [],
    "link": "https://twitter.com/socialistdogmom/status/1034577677108371459",
    "retweet": false,
    "quote_url": "",
    "video": 0,
    "thumbnail": "",
    "near": "",
    "geo": "",
    "source": "",
    "user_rt_id": "",
    "user_rt": "",
    "retweet_id": "",
    "reply_to": [],
    "retweet_date": "",
    "translate": "",
    "trans_src": "",
    "trans_dest": ""
  },
  {
    "id": 1034578050514604037,
    "conversation_id": "1034569419417178112",
    "created_at": "2018-08-28 19:06:43 EDT",
    "date": "2018-08-28",
    "time": "19:06:43",
    "timezone": "-0400",
    "user_id": 85165134,
    "username": "socialistdogmom",
    "name": "molly conger",
    "place": "",
    "tweet": "we\u2019re stuck in an infinite feedback loop. juan says lisa robertson couldn\u2019t answer their questions about privacy concerns until they wrote bylaws but they can\u2019t write bylaws until they understand the legality &amp; confidentiality of collecting the information...",
    "language": "en",
    "mentions": [],
    "urls": [],
    "photos": [],
    "replies_count": 1,
    "retweets_count": 0,
    "likes_count": 1,
    "hashtags": [],
    "cashtags": [],
    "link": "https://twitter.com/socialistdogmom/status/1034578050514604037",
    "retweet": false,
    "quote_url": "",
    "video": 0,
    "thumbnail": "",
    "near": "",
    "geo": "",
    "source": "",
    "user_rt_id": "",
    "user_rt": "",
    "retweet_id": "",
    "reply_to": [],
    "retweet_date": "",
    "translate": "",
    "trans_src": "",
    "trans_dest": ""
  },
  {
    "id": 1034579325562040320,
    "conversation_id": "1034569419417178112",
    "created_at": "2018-08-28 19:11:47 EDT",
    "date": "2018-08-28",
    "time": "19:11:47",
    "timezone": "-0400",
    "user_id": 85165134,
    "username": "socialistdogmom",
    "name": "molly conger",
    "place": "",
    "tweet": "ms rosea raises the issue of the 9th seat the board voted to add to their body. \u201cwe could talk about that as a council, but we\u2019d have to open the process back up and take applications,\u201d says mayor walker.",
    "language": "en",
    "mentions": [],
    "urls": [],
    "photos": [],
    "replies_count": 1,
    "retweets_count": 0,
    "likes_count": 1,
    "hashtags": [],
    "cashtags": [],
    "link": "https://twitter.com/socialistdogmom/status/1034579325562040320",
    "retweet": false,
    "quote_url": "",
    "video": 0,
    "thumbnail": "",
    "near": "",
    "geo": "",
    "source": "",
    "user_rt_id": "",
    "user_rt": "",
    "retweet_id": "",
    "reply_to": [],
    "retweet_date": "",
    "translate": "",
    "trans_src": "",
    "trans_dest": ""
  },
  {
    "id": 1034579328758173696,
    "conversation_id": "1034569419417178112",
    "created_at": "2018-08-28 19:11:48 EDT",
    "date": "2018-08-28",
    "time": "19:11:48",
    "timezone": "-0400",
    "user_id": 85165134,
    "username": "socialistdogmom",
    "name": "molly conger",
    "place": "",
    "tweet": "this isn\u2019t what they did when they added me rosea after the final board had been constituted. they just really, really don\u2019t want jeff fogel on the board. (he\u2019s one of only 2 remaining unselected candidates from the original pool.)",
    "language": "en",
    "mentions": [],
    "urls": [],
    "photos": [],
    "replies_count": 1,
    "retweets_count": 0,
    "likes_count": 1,
    "hashtags": [],
    "cashtags": [],
    "link": "https://twitter.com/socialistdogmom/status/1034579328758173696",
    "retweet": false,
    "quote_url": "",
    "video": 0,
    "thumbnail": "",
    "near": "",
    "geo": "",
    "source": "",
    "user_rt_id": "",
    "user_rt": "",
    "retweet_id": "",
    "reply_to": [],
    "retweet_date": "",
    "translate": "",
    "trans_src": "",
    "trans_dest": ""
  },
  {
    "id": 1034579630584459264,
    "conversation_id": "1034569419417178112",
    "created_at": "2018-08-28 19:13:00 EDT",
    "date": "2018-08-28",
    "time": "19:13:00",
    "timezone": "-0400",
    "user_id": 85165134,
    "username": "socialistdogmom",
    "name": "molly conger",
    "place": "",
    "tweet": "\u201cc\u2019mon heather, why don\u2019t you tell \u2018em why i\u2019m so terrible and i couldn\u2019t possibly serve on this board!\u201d jeff fogel offers from the audience \ud83c\udf36\ud83c\udf36",
    "language": "en",
    "mentions": [],
    "urls": [],
    "photos": [],
    "replies_count": 1,
    "retweets_count": 0,
    "likes_count": 6,
    "hashtags": [],
    "cashtags": [],
    "link": "https://twitter.com/socialistdogmom/status/1034579630584459264",
    "retweet": false,
    "quote_url": "",
    "video": 0,
    "thumbnail": "",
    "near": "",
    "geo": "",
    "source": "",
    "user_rt_id": "",
    "user_rt": "",
    "retweet_id": "",
    "reply_to": [],
    "retweet_date": "",
    "translate": "",
    "trans_src": "",
    "trans_dest": ""
  },
  {
    "id": 1034579888731291649,
    "conversation_id": "1034569419417178112",
    "created_at": "2018-08-28 19:14:01 EDT",
    "date": "2018-08-28",
    "time": "19:14:01",
    "timezone": "-0400",
    "user_id": 85165134,
    "username": "socialistdogmom",
    "name": "molly conger",
    "place": "",
    "tweet": "just a reminder that jeff fogel was the community\u2019s first choice for this board. council chose to disregard this.  https://t.co/ccJfY54KYP",
    "language": "en",
    "mentions": [],
    "urls": [
      "https://twitter.com/socialistdogmom/status/1003786866590666752?s=21"
    ],
    "photos": [],
    "replies_count": 1,
    "retweets_count": 0,
    "likes_count": 5,
    "hashtags": [],
    "cashtags": [],
    "link": "https://twitter.com/socialistdogmom/status/1034579888731291649",
    "retweet": false,
    "quote_url": "https://twitter.com/socialistdogmom/status/1003786866590666752?s=21",
    "video": 0,
    "thumbnail": "",
    "near": "",
    "geo": "",
    "source": "",
    "user_rt_id": "",
    "user_rt": "",
    "retweet_id": "",
    "reply_to": [],
    "retweet_date": "",
    "translate": "",
    "trans_src": "",
    "trans_dest": ""
  },
  {
    "id": 1034580242021658626,
    "conversation_id": "1034569419417178112",
    "created_at": "2018-08-28 19:15:25 EDT",
    "date": "2018-08-28",
    "time": "19:15:25",
    "timezone": "-0400",
    "user_id": 85165134,
    "username": "socialistdogmom",
    "name": "molly conger",
    "place": "",
    "tweet": "re: concerns about 4-4 ties with an eight member body, heather says tie votes don\u2019t pass, citing albemarle county\u2019s 6 person board of supervisors policy on ties.",
    "language": "en",
    "mentions": [],
    "urls": [],
    "photos": [],
    "replies_count": 1,
    "retweets_count": 0,
    "likes_count": 1,
    "hashtags": [],
    "cashtags": [],
    "link": "https://twitter.com/socialistdogmom/status/1034580242021658626",
    "retweet": false,
    "quote_url": "",
    "video": 0,
    "thumbnail": "",
    "near": "",
    "geo": "",
    "source": "",
    "user_rt_id": "",
    "user_rt": "",
    "retweet_id": "",
    "reply_to": [],
    "retweet_date": "",
    "translate": "",
    "trans_src": "",
    "trans_dest": ""
  },
  {
    "id": 1034580537875333121,
    "conversation_id": "1034569419417178112",
    "created_at": "2018-08-28 19:16:36 EDT",
    "date": "2018-08-28",
    "time": "19:16:36",
    "timezone": "-0400",
    "user_id": 85165134,
    "username": "socialistdogmom",
    "name": "molly conger",
    "place": "",
    "tweet": "jeff is now arguing with nikuyah and heather from the audience, with interjections from board member ms katrina.",
    "language": "en",
    "mentions": [],
    "urls": [],
    "photos": [],
    "replies_count": 1,
    "retweets_count": 0,
    "likes_count": 1,
    "hashtags": [],
    "cashtags": [],
    "link": "https://twitter.com/socialistdogmom/status/1034580537875333121",
    "retweet": false,
    "quote_url": "",
    "video": 0,
    "thumbnail": "",
    "near": "",
    "geo": "",
    "source": "",
    "user_rt_id": "",
    "user_rt": "",
    "retweet_id": "",
    "reply_to": [],
    "retweet_date": "",
    "translate": "",
    "trans_src": "",
    "trans_dest": ""
  },
  {
    "id": 1034580541285249025,
    "conversation_id": "1034569419417178112",
    "created_at": "2018-08-28 19:16:37 EDT",
    "date": "2018-08-28",
    "time": "19:16:37",
    "timezone": "-0400",
    "user_id": 85165134,
    "username": "socialistdogmom",
    "name": "molly conger",
    "place": "",
    "tweet": "heather hill says, petulantly, \u201ci\u2019m really just here to support this board.\u201d this is met with loud laughter from the audience.",
    "language": "en",
    "mentions": [],
    "urls": [],
    "photos": [],
    "replies_count": 3,
    "retweets_count": 0,
    "likes_count": 9,
    "hashtags": [],
    "cashtags": [],
    "link": "https://twitter.com/socialistdogmom/status/1034580541285249025",
    "retweet": false,
    "quote_url": "",
    "video": 0,
    "thumbnail": "",
    "near": "",
    "geo": "",
    "source": "",
    "user_rt_id": "",
    "user_rt": "",
    "retweet_id": "",
    "reply_to": [],
    "retweet_date": "",
    "translate": "",
    "trans_src": "",
    "trans_dest": ""
  },
  {
    "id": 1034581233307709440,
    "conversation_id": "1034569419417178112",
    "created_at": "2018-08-28 19:19:22 EDT",
    "date": "2018-08-28",
    "time": "19:19:22",
    "timezone": "-0400",
    "user_id": 85165134,
    "username": "socialistdogmom",
    "name": "molly conger",
    "place": "",
    "tweet": "don asks if there is any way to appoint a member from the existing pool. nikuyah says \u201cthe way this board is being scrutinized, i would say no.\u201d sarah asks what happens if someone resigns. nikuyah says they\u2019d reopen the application process &amp; start over with a new appointment.",
    "language": "en",
    "mentions": [],
    "urls": [],
    "photos": [],
    "replies_count": 1,
    "retweets_count": 0,
    "likes_count": 1,
    "hashtags": [],
    "cashtags": [],
    "link": "https://twitter.com/socialistdogmom/status/1034581233307709440",
    "retweet": false,
    "quote_url": "",
    "video": 0,
    "thumbnail": "",
    "near": "",
    "geo": "",
    "source": "",
    "user_rt_id": "",
    "user_rt": "",
    "retweet_id": "",
    "reply_to": [],
    "retweet_date": "",
    "translate": "",
    "trans_src": "",
    "trans_dest": ""
  },
  {
    "id": 1034581236755439621,
    "conversation_id": "1034569419417178112",
    "created_at": "2018-08-28 19:19:23 EDT",
    "date": "2018-08-28",
    "time": "19:19:23",
    "timezone": "-0400",
    "user_id": 85165134,
    "username": "socialistdogmom",
    "name": "molly conger",
    "place": "",
    "tweet": "a city staffer in the audience says the board can create subcommittees and add people to those, those people just don\u2019t get a vote on board matters. a community member who has served on city boards before offers that boards can invite anyone to sit with them.",
    "language": "en",
    "mentions": [],
    "urls": [],
    "photos": [],
    "replies_count": 1,
    "retweets_count": 0,
    "likes_count": 1,
    "hashtags": [],
    "cashtags": [],
    "link": "https://twitter.com/socialistdogmom/status/1034581236755439621",
    "retweet": false,
    "quote_url": "",
    "video": 0,
    "thumbnail": "",
    "near": "",
    "geo": "",
    "source": "",
    "user_rt_id": "",
    "user_rt": "",
    "retweet_id": "",
    "reply_to": [],
    "retweet_date": "",
    "translate": "",
    "trans_src": "",
    "trans_dest": ""
  },
  {
    "id": 1034581501751582720,
    "conversation_id": "1034569419417178112",
    "created_at": "2018-08-28 19:20:26 EDT",
    "date": "2018-08-28",
    "time": "19:20:26",
    "timezone": "-0400",
    "user_id": 85165134,
    "username": "socialistdogmom",
    "name": "molly conger",
    "place": "",
    "tweet": "it seems like they could easily have jeff work with them in every capacity short of having an official vote. that seems like good enough? why fight a losing battle with an intractable council?",
    "language": "en",
    "mentions": [],
    "urls": [],
    "photos": [],
    "replies_count": 1,
    "retweets_count": 0,
    "likes_count": 5,
    "hashtags": [],
    "cashtags": [],
    "link": "https://twitter.com/socialistdogmom/status/1034581501751582720",
    "retweet": false,
    "quote_url": "",
    "video": 0,
    "thumbnail": "",
    "near": "",
    "geo": "",
    "source": "",
    "user_rt_id": "",
    "user_rt": "",
    "retweet_id": "",
    "reply_to": [],
    "retweet_date": "",
    "translate": "",
    "trans_src": "",
    "trans_dest": ""
  },
  {
    "id": 1034581843956453376,
    "conversation_id": "1034569419417178112",
    "created_at": "2018-08-28 19:21:47 EDT",
    "date": "2018-08-28",
    "time": "19:21:47",
    "timezone": "-0400",
    "user_id": 85165134,
    "username": "socialistdogmom",
    "name": "molly conger",
    "place": "",
    "tweet": "\u201ci don\u2019t believe that you have the capacity to be objective on this,\u201d heather tells jeff fogel as he gets up to leave, addressing her again as he reaches the door.",
    "language": "en",
    "mentions": [],
    "urls": [],
    "photos": [],
    "replies_count": 2,
    "retweets_count": 0,
    "likes_count": 3,
    "hashtags": [],
    "cashtags": [],
    "link": "https://twitter.com/socialistdogmom/status/1034581843956453376",
    "retweet": false,
    "quote_url": "",
    "video": 0,
    "thumbnail": "",
    "near": "",
    "geo": "",
    "source": "",
    "user_rt_id": "",
    "user_rt": "",
    "retweet_id": "",
    "reply_to": [],
    "retweet_date": "",
    "translate": "",
    "trans_src": "",
    "trans_dest": ""
  },
  {
    "id": 1034582359755186177,
    "conversation_id": "1034569419417178112",
    "created_at": "2018-08-28 19:23:50 EDT",
    "date": "2018-08-28",
    "time": "19:23:50",
    "timezone": "-0400",
    "user_id": 85165134,
    "username": "socialistdogmom",
    "name": "molly conger",
    "place": "",
    "tweet": "moving on. sarah burke talking now about past discussion about having a liaison on city council, someone who could attend their meetings. this is a common practice with other city boards &amp; commissions. nikuyah says council would have to vote on this.",
    "language": "en",
    "mentions": [],
    "urls": [],
    "photos": [],
    "replies_count": 1,
    "retweets_count": 0,
    "likes_count": 2,
    "hashtags": [],
    "cashtags": [],
    "link": "https://twitter.com/socialistdogmom/status/1034582359755186177",
    "retweet": false,
    "quote_url": "",
    "video": 0,
    "thumbnail": "",
    "near": "",
    "geo": "",
    "source": "",
    "user_rt_id": "",
    "user_rt": "",
    "retweet_id": "",
    "reply_to": [],
    "retweet_date": "",
    "translate": "",
    "trans_src": "",
    "trans_dest": ""
  },
  {
    "id": 1034582898450554880,
    "conversation_id": "1034569419417178112",
    "created_at": "2018-08-28 19:25:59 EDT",
    "date": "2018-08-28",
    "time": "19:25:59",
    "timezone": "-0400",
    "user_id": 85165134,
    "username": "socialistdogmom",
    "name": "molly conger",
    "place": "",
    "tweet": "board member josh bowers asks why they have to vote on this? it doesn\u2019t even need to be official, they just need a liaison.",
    "language": "en",
    "mentions": [],
    "urls": [],
    "photos": [],
    "replies_count": 1,
    "retweets_count": 0,
    "likes_count": 1,
    "hashtags": [],
    "cashtags": [],
    "link": "https://twitter.com/socialistdogmom/status/1034582898450554880",
    "retweet": false,
    "quote_url": "",
    "video": 0,
    "thumbnail": "",
    "near": "",
    "geo": "",
    "source": "",
    "user_rt_id": "",
    "user_rt": "",
    "retweet_id": "",
    "reply_to": [],
    "retweet_date": "",
    "translate": "",
    "trans_src": "",
    "trans_dest": ""
  },
  {
    "id": 1034582901894078466,
    "conversation_id": "1034569419417178112",
    "created_at": "2018-08-28 19:26:00 EDT",
    "date": "2018-08-28",
    "time": "19:26:00",
    "timezone": "-0400",
    "user_id": 85165134,
    "username": "socialistdogmom",
    "name": "molly conger",
    "place": "",
    "tweet": "vice mayor heather hill nervously and breathlessly explains the need for council to discuss amongst themselves who would serve as liaison, based on their schedules. she says she knows she\u2019s not the one people want on this... to which the audience offers agreement.",
    "language": "en",
    "mentions": [],
    "urls": [],
    "photos": [],
    "replies_count": 1,
    "retweets_count": 0,
    "likes_count": 3,
    "hashtags": [],
    "cashtags": [],
    "link": "https://twitter.com/socialistdogmom/status/1034582901894078466",
    "retweet": false,
    "quote_url": "",
    "video": 0,
    "thumbnail": "",
    "near": "",
    "geo": "",
    "source": "",
    "user_rt_id": "",
    "user_rt": "",
    "retweet_id": "",
    "reply_to": [],
    "retweet_date": "",
    "translate": "",
    "trans_src": "",
    "trans_dest": ""
  },
  {
    "id": 1034583298624966659,
    "conversation_id": "1034569419417178112",
    "created_at": "2018-08-28 19:27:34 EDT",
    "date": "2018-08-28",
    "time": "19:27:34",
    "timezone": "-0400",
    "user_id": 85165134,
    "username": "socialistdogmom",
    "name": "molly conger",
    "place": "",
    "tweet": "board member gloria beard says they need a council liaison at meetings - like they\u2019re doing right now, they need council input on a lot of questions. having immediate answers is necessary to keep business moving.",
    "language": "en",
    "mentions": [],
    "urls": [],
    "photos": [],
    "replies_count": 1,
    "retweets_count": 0,
    "likes_count": 2,
    "hashtags": [],
    "cashtags": [],
    "link": "https://twitter.com/socialistdogmom/status/1034583298624966659",
    "retweet": false,
    "quote_url": "",
    "video": 0,
    "thumbnail": "",
    "near": "",
    "geo": "",
    "source": "",
    "user_rt_id": "",
    "user_rt": "",
    "retweet_id": "",
    "reply_to": [],
    "retweet_date": "",
    "translate": "",
    "trans_src": "",
    "trans_dest": ""
  },
  {
    "id": 1034584100248723456,
    "conversation_id": "1034569419417178112",
    "created_at": "2018-08-28 19:30:45 EDT",
    "date": "2018-08-28",
    "time": "19:30:45",
    "timezone": "-0400",
    "user_id": 85165134,
    "username": "socialistdogmom",
    "name": "molly conger",
    "place": "",
    "tweet": "heather says they\u2019re happy to have someone attend meetings but if it\u2019s going to be a formal arrangement, they need to make a request to council and have council vote on it. sarah says she\u2019s like a formal arrangement, don disagrees. \u201cthis is our board.\u201d",
    "language": "en",
    "mentions": [],
    "urls": [],
    "photos": [],
    "replies_count": 1,
    "retweets_count": 0,
    "likes_count": 2,
    "hashtags": [],
    "cashtags": [],
    "link": "https://twitter.com/socialistdogmom/status/1034584100248723456",
    "retweet": false,
    "quote_url": "",
    "video": 0,
    "thumbnail": "",
    "near": "",
    "geo": "",
    "source": "",
    "user_rt_id": "",
    "user_rt": "",
    "retweet_id": "",
    "reply_to": [],
    "retweet_date": "",
    "translate": "",
    "trans_src": "",
    "trans_dest": ""
  },
  {
    "id": 1034585098010669056,
    "conversation_id": "1034569419417178112",
    "created_at": "2018-08-28 19:34:43 EDT",
    "date": "2018-08-28",
    "time": "19:34:43",
    "timezone": "-0400",
    "user_id": 85165134,
    "username": "socialistdogmom",
    "name": "molly conger",
    "place": "",
    "tweet": "\u201cwe usually sign up for boards that we\u2019re passionate about,\u201d nikuyah says of the usual formal process for assigning council members to boards and commissions.",
    "language": "en",
    "mentions": [],
    "urls": [],
    "photos": [],
    "replies_count": 1,
    "retweets_count": 0,
    "likes_count": 1,
    "hashtags": [],
    "cashtags": [],
    "link": "https://twitter.com/socialistdogmom/status/1034585098010669056",
    "retweet": false,
    "quote_url": "",
    "video": 0,
    "thumbnail": "",
    "near": "",
    "geo": "",
    "source": "",
    "user_rt_id": "",
    "user_rt": "",
    "retweet_id": "",
    "reply_to": [],
    "retweet_date": "",
    "translate": "",
    "trans_src": "",
    "trans_dest": ""
  },
  {
    "id": 1034585101802373120,
    "conversation_id": "1034569419417178112",
    "created_at": "2018-08-28 19:34:44 EDT",
    "date": "2018-08-28",
    "time": "19:34:44",
    "timezone": "-0400",
    "user_id": 85165134,
    "username": "socialistdogmom",
    "name": "molly conger",
    "place": "",
    "tweet": "\u201cwe elected them. we don\u2019t get to sit at their table,\u201d don says, arguing against letting a councilmember sit at the table with them on this board.  \u201ci don\u2019t think anybody wants that,\u201d says sarah (of council having input on the direction of the board)",
    "language": "en",
    "mentions": [],
    "urls": [],
    "photos": [],
    "replies_count": 1,
    "retweets_count": 0,
    "likes_count": 2,
    "hashtags": [],
    "cashtags": [],
    "link": "https://twitter.com/socialistdogmom/status/1034585101802373120",
    "retweet": false,
    "quote_url": "",
    "video": 0,
    "thumbnail": "",
    "near": "",
    "geo": "",
    "source": "",
    "user_rt_id": "",
    "user_rt": "",
    "retweet_id": "",
    "reply_to": [],
    "retweet_date": "",
    "translate": "",
    "trans_src": "",
    "trans_dest": ""
  },
  {
    "id": 1034586183366524928,
    "conversation_id": "1034569419417178112",
    "created_at": "2018-08-28 19:39:02 EDT",
    "date": "2018-08-28",
    "time": "19:39:02",
    "timezone": "-0400",
    "user_id": 85165134,
    "username": "socialistdogmom",
    "name": "molly conger",
    "place": "",
    "tweet": "\u201cthat\u2019s possible i guess, for some... we participate,\u201d nikuyah says to sarah burke, who asked if it was possible for a council member to just sit &amp; listen &amp; report back to council?",
    "language": "en",
    "mentions": [],
    "urls": [],
    "photos": [],
    "replies_count": 1,
    "retweets_count": 0,
    "likes_count": 3,
    "hashtags": [],
    "cashtags": [],
    "link": "https://twitter.com/socialistdogmom/status/1034586183366524928",
    "retweet": false,
    "quote_url": "",
    "video": 0,
    "thumbnail": "",
    "near": "",
    "geo": "",
    "source": "",
    "user_rt_id": "",
    "user_rt": "",
    "retweet_id": "",
    "reply_to": [],
    "retweet_date": "",
    "translate": "",
    "trans_src": "",
    "trans_dest": ""
  },
  {
    "id": 1034586326673379328,
    "conversation_id": "1034569419417178112",
    "created_at": "2018-08-28 19:39:36 EDT",
    "date": "2018-08-28",
    "time": "19:39:36",
    "timezone": "-0400",
    "user_id": 85165134,
    "username": "socialistdogmom",
    "name": "molly conger",
    "place": "",
    "tweet": "board member gloria beard is frustrated. \u201cwe gotta get started!\u201d she wants to move past this question and just get down to business.",
    "language": "en",
    "mentions": [],
    "urls": [],
    "photos": [],
    "replies_count": 1,
    "retweets_count": 0,
    "likes_count": 1,
    "hashtags": [],
    "cashtags": [],
    "link": "https://twitter.com/socialistdogmom/status/1034586326673379328",
    "retweet": false,
    "quote_url": "",
    "video": 0,
    "thumbnail": "",
    "near": "",
    "geo": "",
    "source": "",
    "user_rt_id": "",
    "user_rt": "",
    "retweet_id": "",
    "reply_to": [],
    "retweet_date": "",
    "translate": "",
    "trans_src": "",
    "trans_dest": ""
  },
  {
    "id": 1034586618177437696,
    "conversation_id": "1034569419417178112",
    "created_at": "2018-08-28 19:40:46 EDT",
    "date": "2018-08-28",
    "time": "19:40:46",
    "timezone": "-0400",
    "user_id": 85165134,
    "username": "socialistdogmom",
    "name": "molly conger",
    "place": "",
    "tweet": "\u201cit seems like there\u2019s not enthusiasm for this at this point. let\u2019s just table it,\u201d josh says. motion to table passes. heather, nikuyah, and city attorney john blair get up &amp; leave.",
    "language": "en",
    "mentions": [],
    "urls": [],
    "photos": [],
    "replies_count": 1,
    "retweets_count": 0,
    "likes_count": 1,
    "hashtags": [],
    "cashtags": [],
    "link": "https://twitter.com/socialistdogmom/status/1034586618177437696",
    "retweet": false,
    "quote_url": "",
    "video": 0,
    "thumbnail": "",
    "near": "",
    "geo": "",
    "source": "",
    "user_rt_id": "",
    "user_rt": "",
    "retweet_id": "",
    "reply_to": [],
    "retweet_date": "",
    "translate": "",
    "trans_src": "",
    "trans_dest": ""
  },
  {
    "id": 1034586973359484928,
    "conversation_id": "1034569419417178112",
    "created_at": "2018-08-28 19:42:10 EDT",
    "date": "2018-08-28",
    "time": "19:42:10",
    "timezone": "-0400",
    "user_id": 85165134,
    "username": "socialistdogmom",
    "name": "molly conger",
    "place": "",
    "tweet": "we\u2019ve gone very out of order. over an hour into the meeting, we\u2019re just getting to the new business portion, a presentation from LAJC &amp; some law students on CRBs in other localities.  https://t.co/EwWNweOPXK",
    "language": "en",
    "mentions": [],
    "urls": [],
    "photos": [
      "https://pbs.twimg.com/media/DluXW0HX0AEXciD.jpg"
    ],
    "replies_count": 1,
    "retweets_count": 0,
    "likes_count": 2,
    "hashtags": [],
    "cashtags": [],
    "link": "https://twitter.com/socialistdogmom/status/1034586973359484928",
    "retweet": false,
    "quote_url": "",
    "video": 1,
    "thumbnail": "https://pbs.twimg.com/media/DluXW0HX0AEXciD.jpg",
    "near": "",
    "geo": "",
    "source": "",
    "user_rt_id": "",
    "user_rt": "",
    "retweet_id": "",
    "reply_to": [],
    "retweet_date": "",
    "translate": "",
    "trans_src": "",
    "trans_dest": ""
  },
  {
    "id": 1034587930986250240,
    "conversation_id": "1034569419417178112",
    "created_at": "2018-08-28 19:45:59 EDT",
    "date": "2018-08-28",
    "time": "19:45:59",
    "timezone": "-0400",
    "user_id": 85165134,
    "username": "socialistdogmom",
    "name": "molly conger",
    "place": "",
    "tweet": "presentation starts with the community\u2019s desires for the board: for it to have accesss to police records, to be transparent, to have power to affect policy. (the board is already struggling with most of these points)",
    "language": "en",
    "mentions": [],
    "urls": [],
    "photos": [],
    "replies_count": 1,
    "retweets_count": 0,
    "likes_count": 3,
    "hashtags": [],
    "cashtags": [],
    "link": "https://twitter.com/socialistdogmom/status/1034587930986250240",
    "retweet": false,
    "quote_url": "",
    "video": 0,
    "thumbnail": "",
    "near": "",
    "geo": "",
    "source": "",
    "user_rt_id": "",
    "user_rt": "",
    "retweet_id": "",
    "reply_to": [],
    "retweet_date": "",
    "translate": "",
    "trans_src": "",
    "trans_dest": ""
  },
  {
    "id": 1034588482948280320,
    "conversation_id": "1034569419417178112",
    "created_at": "2018-08-28 19:48:10 EDT",
    "date": "2018-08-28",
    "time": "19:48:10",
    "timezone": "-0400",
    "user_id": 85165134,
    "username": "socialistdogmom",
    "name": "molly conger",
    "place": "",
    "tweet": "this is useful background for the board members - the city should\u2019ve provided a lot of this information at the outset. just defining what the board is &amp; does in other cities.",
    "language": "en",
    "mentions": [],
    "urls": [],
    "photos": [],
    "replies_count": 1,
    "retweets_count": 0,
    "likes_count": 2,
    "hashtags": [],
    "cashtags": [],
    "link": "https://twitter.com/socialistdogmom/status/1034588482948280320",
    "retweet": false,
    "quote_url": "",
    "video": 0,
    "thumbnail": "",
    "near": "",
    "geo": "",
    "source": "",
    "user_rt_id": "",
    "user_rt": "",
    "retweet_id": "",
    "reply_to": [],
    "retweet_date": "",
    "translate": "",
    "trans_src": "",
    "trans_dest": ""
  },
  {
    "id": 1034590854181257217,
    "conversation_id": "1034569419417178112",
    "created_at": "2018-08-28 19:57:36 EDT",
    "date": "2018-08-28",
    "time": "19:57:36",
    "timezone": "-0400",
    "user_id": 85165134,
    "username": "socialistdogmom",
    "name": "molly conger",
    "place": "",
    "tweet": "while CRBs do not typically have subpoena powers, there are possibilities here - they could have an executive director who is technically employed by the city who would then have subpoena power.  https://t.co/AfY0D8R3HR",
    "language": "en",
    "mentions": [],
    "urls": [],
    "photos": [
      "https://pbs.twimg.com/media/Dlua3-ZXcAEt2pX.jpg",
      "https://pbs.twimg.com/media/Dlua3-XXsAERdBL.jpg"
    ],
    "replies_count": 1,
    "retweets_count": 0,
    "likes_count": 3,
    "hashtags": [],
    "cashtags": [],
    "link": "https://twitter.com/socialistdogmom/status/1034590854181257217",
    "retweet": false,
    "quote_url": "",
    "video": 1,
    "thumbnail": "https://pbs.twimg.com/media/Dlua3-ZXcAEt2pX.jpg",
    "near": "",
    "geo": "",
    "source": "",
    "user_rt_id": "",
    "user_rt": "",
    "retweet_id": "",
    "reply_to": [],
    "retweet_date": "",
    "translate": "",
    "trans_src": "",
    "trans_dest": ""
  },
  {
    "id": 1034590858132242433,
    "conversation_id": "1034569419417178112",
    "created_at": "2018-08-28 19:57:37 EDT",
    "date": "2018-08-28",
    "time": "19:57:37",
    "timezone": "-0400",
    "user_id": 85165134,
    "username": "socialistdogmom",
    "name": "molly conger",
    "place": "",
    "tweet": "the human rights commission has subpoena power, but these types of boards are specifically granted that power by the virginia code.",
    "language": "en",
    "mentions": [],
    "urls": [],
    "photos": [],
    "replies_count": 1,
    "retweets_count": 0,
    "likes_count": 2,
    "hashtags": [],
    "cashtags": [],
    "link": "https://twitter.com/socialistdogmom/status/1034590858132242433",
    "retweet": false,
    "quote_url": "",
    "video": 0,
    "thumbnail": "",
    "near": "",
    "geo": "",
    "source": "",
    "user_rt_id": "",
    "user_rt": "",
    "retweet_id": "",
    "reply_to": [],
    "retweet_date": "",
    "translate": "",
    "trans_src": "",
    "trans_dest": ""
  },
  {
    "id": 1034591096574300160,
    "conversation_id": "1034569419417178112",
    "created_at": "2018-08-28 19:58:33 EDT",
    "date": "2018-08-28",
    "time": "19:58:33",
    "timezone": "-0400",
    "user_id": 85165134,
    "username": "socialistdogmom",
    "name": "molly conger",
    "place": "",
    "tweet": "some cities offer a nominal payment to board members, which technically makes them employees of the city, which could grant the board subpoena power. the law student says, \u201cyou would probably get pushback on that.\u201d",
    "language": "en",
    "mentions": [],
    "urls": [],
    "photos": [],
    "replies_count": 1,
    "retweets_count": 0,
    "likes_count": 1,
    "hashtags": [],
    "cashtags": [],
    "link": "https://twitter.com/socialistdogmom/status/1034591096574300160",
    "retweet": false,
    "quote_url": "",
    "video": 0,
    "thumbnail": "",
    "near": "",
    "geo": "",
    "source": "",
    "user_rt_id": "",
    "user_rt": "",
    "retweet_id": "",
    "reply_to": [],
    "retweet_date": "",
    "translate": "",
    "trans_src": "",
    "trans_dest": ""
  },
  {
    "id": 1034591816946012165,
    "conversation_id": "1034569419417178112",
    "created_at": "2018-08-28 20:01:25 EDT",
    "date": "2018-08-28",
    "time": "20:01:25",
    "timezone": "-0400",
    "user_id": 85165134,
    "username": "socialistdogmom",
    "name": "molly conger",
    "place": "",
    "tweet": "the board\u2019s suggestion that they might collect complaints independently &amp; conduct their own investigations seems inconsistent with how other bodies function.  https://t.co/QSFL0ZGM2P",
    "language": "en",
    "mentions": [],
    "urls": [],
    "photos": [
      "https://pbs.twimg.com/media/Dlubw1WWsAA4hNa.jpg"
    ],
    "replies_count": 1,
    "retweets_count": 0,
    "likes_count": 2,
    "hashtags": [],
    "cashtags": [],
    "link": "https://twitter.com/socialistdogmom/status/1034591816946012165",
    "retweet": false,
    "quote_url": "",
    "video": 1,
    "thumbnail": "https://pbs.twimg.com/media/Dlubw1WWsAA4hNa.jpg",
    "near": "",
    "geo": "",
    "source": "",
    "user_rt_id": "",
    "user_rt": "",
    "retweet_id": "",
    "reply_to": [],
    "retweet_date": "",
    "translate": "",
    "trans_src": "",
    "trans_dest": ""
  },
  {
    "id": 1034594188971655168,
    "conversation_id": "1034569419417178112",
    "created_at": "2018-08-28 20:10:51 EDT",
    "date": "2018-08-28",
    "time": "20:10:51",
    "timezone": "-0400",
    "user_id": 85165134,
    "username": "socialistdogmom",
    "name": "molly conger",
    "place": "",
    "tweet": "the law student giving the presentation says the board absolutely has the right to hold public meetings &amp; get community comment even before fully completing their bylaws, \u201cdon\u2019t let anyone tell you different.\u201d",
    "language": "en",
    "mentions": [],
    "urls": [],
    "photos": [],
    "replies_count": 1,
    "retweets_count": 0,
    "likes_count": 4,
    "hashtags": [],
    "cashtags": [],
    "link": "https://twitter.com/socialistdogmom/status/1034594188971655168",
    "retweet": false,
    "quote_url": "",
    "video": 0,
    "thumbnail": "",
    "near": "",
    "geo": "",
    "source": "",
    "user_rt_id": "",
    "user_rt": "",
    "retweet_id": "",
    "reply_to": [],
    "retweet_date": "",
    "translate": "",
    "trans_src": "",
    "trans_dest": ""
  },
  {
    "id": 1034597991586430982,
    "conversation_id": "1034569419417178112",
    "created_at": "2018-08-28 20:25:57 EDT",
    "date": "2018-08-28",
    "time": "20:25:57",
    "timezone": "-0400",
    "user_id": 85165134,
    "username": "socialistdogmom",
    "name": "molly conger",
    "place": "",
    "tweet": "board members are discussing attending a CRB meeting in one of the cities discussed in the presentation. fairfax county\u2019s meetings are recorded and available online, but charlotte, NC has a more similar style of city government.",
    "language": "en",
    "mentions": [],
    "urls": [],
    "photos": [],
    "replies_count": 1,
    "retweets_count": 0,
    "likes_count": 1,
    "hashtags": [],
    "cashtags": [],
    "link": "https://twitter.com/socialistdogmom/status/1034597991586430982",
    "retweet": false,
    "quote_url": "",
    "video": 0,
    "thumbnail": "",
    "near": "",
    "geo": "",
    "source": "",
    "user_rt_id": "",
    "user_rt": "",
    "retweet_id": "",
    "reply_to": [],
    "retweet_date": "",
    "translate": "",
    "trans_src": "",
    "trans_dest": ""
  },
  {
    "id": 1034601104217133056,
    "conversation_id": "1034569419417178112",
    "created_at": "2018-08-28 20:38:19 EDT",
    "date": "2018-08-28",
    "time": "20:38:19",
    "timezone": "-0400",
    "user_id": 85165134,
    "username": "socialistdogmom",
    "name": "molly conger",
    "place": "",
    "tweet": "board member guillermo ubilla says he would like to meet with the city attorney about some questions he has. gloria beard would like to meet with the police chief. the board laughs when ms rosea says she doesn\u2019t want to be a part of that meeting.",
    "language": "en",
    "mentions": [],
    "urls": [],
    "photos": [],
    "replies_count": 1,
    "retweets_count": 0,
    "likes_count": 2,
    "hashtags": [],
    "cashtags": [],
    "link": "https://twitter.com/socialistdogmom/status/1034601104217133056",
    "retweet": false,
    "quote_url": "",
    "video": 0,
    "thumbnail": "",
    "near": "",
    "geo": "",
    "source": "",
    "user_rt_id": "",
    "user_rt": "",
    "retweet_id": "",
    "reply_to": [],
    "retweet_date": "",
    "translate": "",
    "trans_src": "",
    "trans_dest": ""
  },
  {
    "id": 1034601106356273152,
    "conversation_id": "1034569419417178112",
    "created_at": "2018-08-28 20:38:20 EDT",
    "date": "2018-08-28",
    "time": "20:38:20",
    "timezone": "-0400",
    "user_id": 85165134,
    "username": "socialistdogmom",
    "name": "molly conger",
    "place": "",
    "tweet": "ms katrina says the police chief told her she \u201cdoesn\u2019t know if she\u2019s allowed\u201d to provide police department policies to her. sarah burke says she\u2019s FOIA\u2019ed a lot of this information already and will provide what she has.",
    "language": "en",
    "mentions": [],
    "urls": [],
    "photos": [],
    "replies_count": 1,
    "retweets_count": 0,
    "likes_count": 5,
    "hashtags": [],
    "cashtags": [],
    "link": "https://twitter.com/socialistdogmom/status/1034601106356273152",
    "retweet": false,
    "quote_url": "",
    "video": 0,
    "thumbnail": "",
    "near": "",
    "geo": "",
    "source": "",
    "user_rt_id": "",
    "user_rt": "",
    "retweet_id": "",
    "reply_to": [],
    "retweet_date": "",
    "translate": "",
    "trans_src": "",
    "trans_dest": ""
  },
  {
    "id": 1034605145622028289,
    "conversation_id": "1034569419417178112",
    "created_at": "2018-08-28 20:54:23 EDT",
    "date": "2018-08-28",
    "time": "20:54:23",
    "timezone": "-0400",
    "user_id": 85165134,
    "username": "socialistdogmom",
    "name": "molly conger",
    "place": "",
    "tweet": "the board has been working on forming up subcommittees and assigning next steps to members. there\u2019s a lot of cross talk and the vibe is very casual &amp; conversational.",
    "language": "en",
    "mentions": [],
    "urls": [],
    "photos": [],
    "replies_count": 1,
    "retweets_count": 0,
    "likes_count": 2,
    "hashtags": [],
    "cashtags": [],
    "link": "https://twitter.com/socialistdogmom/status/1034605145622028289",
    "retweet": false,
    "quote_url": "",
    "video": 0,
    "thumbnail": "",
    "near": "",
    "geo": "",
    "source": "",
    "user_rt_id": "",
    "user_rt": "",
    "retweet_id": "",
    "reply_to": [],
    "retweet_date": "",
    "translate": "",
    "trans_src": "",
    "trans_dest": ""
  },
  {
    "id": 1034605753313710080,
    "conversation_id": "1034569419417178112",
    "created_at": "2018-08-28 20:56:48 EDT",
    "date": "2018-08-28",
    "time": "20:56:48",
    "timezone": "-0400",
    "user_id": 85165134,
    "username": "socialistdogmom",
    "name": "molly conger",
    "place": "",
    "tweet": "harold folley from LAJC asks the board if they plan to contact fairfax &amp; virginia beach to find out what kind of budgets their CRBs operate with. josh bowers said it should be as simple as a couple of phone calls.",
    "language": "en",
    "mentions": [],
    "urls": [],
    "photos": [],
    "replies_count": 1,
    "retweets_count": 0,
    "likes_count": 1,
    "hashtags": [],
    "cashtags": [],
    "link": "https://twitter.com/socialistdogmom/status/1034605753313710080",
    "retweet": false,
    "quote_url": "",
    "video": 0,
    "thumbnail": "",
    "near": "",
    "geo": "",
    "source": "",
    "user_rt_id": "",
    "user_rt": "",
    "retweet_id": "",
    "reply_to": [],
    "retweet_date": "",
    "translate": "",
    "trans_src": "",
    "trans_dest": ""
  },
  {
    "id": 1034606040187396097,
    "conversation_id": "1034569419417178112",
    "created_at": "2018-08-28 20:57:56 EDT",
    "date": "2018-08-28",
    "time": "20:57:56",
    "timezone": "-0400",
    "user_id": 85165134,
    "username": "socialistdogmom",
    "name": "molly conger",
    "place": "",
    "tweet": "the board\u2019s current budget is $2500. this obviously won\u2019t cover outside counsel, travel to other cities\u2019 board meetings, and full dinner provided to all board members at every meeting (an issue don has raised at every meeting so far)",
    "language": "en",
    "mentions": [],
    "urls": [],
    "photos": [],
    "replies_count": 1,
    "retweets_count": 0,
    "likes_count": 2,
    "hashtags": [],
    "cashtags": [],
    "link": "https://twitter.com/socialistdogmom/status/1034606040187396097",
    "retweet": false,
    "quote_url": "",
    "video": 0,
    "thumbnail": "",
    "near": "",
    "geo": "",
    "source": "",
    "user_rt_id": "",
    "user_rt": "",
    "retweet_id": "",
    "reply_to": [],
    "retweet_date": "",
    "translate": "",
    "trans_src": "",
    "trans_dest": ""
  },
  {
    "id": 1034607714960334848,
    "conversation_id": "1034569419417178112",
    "created_at": "2018-08-28 21:04:35 EDT",
    "date": "2018-08-28",
    "time": "21:04:35",
    "timezone": "-0400",
    "user_id": 85165134,
    "username": "socialistdogmom",
    "name": "molly conger",
    "place": "",
    "tweet": "the next meeting will be on september 11. the website shows it\u2019ll be in this same basement conference room, but the board agrees this is insufficient. they\u2019re discussing alternatives, including council chambers &amp; cityspace. the library is a tough sell due to a 9pm closing time.",
    "language": "en",
    "mentions": [],
    "urls": [],
    "photos": [],
    "replies_count": 2,
    "retweets_count": 0,
    "likes_count": 3,
    "hashtags": [],
    "cashtags": [],
    "link": "https://twitter.com/socialistdogmom/status/1034607714960334848",
    "retweet": false,
    "quote_url": "",
    "video": 0,
    "thumbnail": "",
    "near": "",
    "geo": "",
    "source": "",
    "user_rt_id": "",
    "user_rt": "",
    "retweet_id": "",
    "reply_to": [],
    "retweet_date": "",
    "translate": "",
    "trans_src": "",
    "trans_dest": ""
  },
  {
    "id": 1034608576734670848,
    "conversation_id": "1034569419417178112",
    "created_at": "2018-08-28 21:08:01 EDT",
    "date": "2018-08-28",
    "time": "21:08:01",
    "timezone": "-0400",
    "user_id": 85165134,
    "username": "socialistdogmom",
    "name": "molly conger",
    "place": "",
    "tweet": "the board has not elected any officers and is instead using a system of rotating chairs and notetakers. josh bowers will chair september meetings with notes taken by sarah burke. meeting adjourned. location of the 9/11 meeting is still TBD.",
    "language": "en",
    "mentions": [],
    "urls": [],
    "photos": [],
    "replies_count": 0,
    "retweets_count": 0,
    "likes_count": 3,
    "hashtags": [],
    "cashtags": [],
    "link": "https://twitter.com/socialistdogmom/status/1034608576734670848",
    "retweet": false,
    "quote_url": "",
    "video": 0,
    "thumbnail": "",
    "near": "",
    "geo": "",
    "source": "",
    "user_rt_id": "",
    "user_rt": "",
    "retweet_id": "",
    "reply_to": [],
    "retweet_date": "",
    "translate": "",
    "trans_src": "",
    "trans_dest": ""
  }
]